MANIFEST.in
README.md
README.rst
setup.py
prest/__init__.py
prest/basic.py
prest/example.py
prest/orm.py
prest/test_basic.py
prest/test_orm.py
prest.egg-info/PKG-INFO
prest.egg-info/SOURCES.txt
prest.egg-info/dependency_links.txt
prest.egg-info/not-zip-safe
prest.egg-info/top_level.txt