Metadata-Version: 1.0
Name: prest
Version: 0.3
Summary: This module makes writing client API for REST services as easy as GET('my_api/{some_param}')
Home-page: https://github.com/koder-ua/prest
Author: K.Danilov aka koder
Author-email: koder.mail@gmail.com
License: LGPL
Platform: UNKNOWN
